{
  "title": "Welcome to Split Lease",
  "url": "https://www.split.lease/",
  "description": "Commuting or Traveling? Rent a home by nights-of-the-week or weeks of the month. Live in multiple cities or skip your commute. Pay for the space, not cleaning fees and taxes. Have a space to share? Make predictable income by hosting repeat guests.",
  "screenshot_location": "C:\\Users\\Split Lease\\Documents\\Claude\\.playwright-mcp\\split-lease-full-page.png",
  "page_text": "Ongoing Rentals for Repeat Stays\nSelect which days you'd like to stay in NYC and only pay for the nights you need.\nS M T W T F S\nExplore Rentals\nOnly pay for nights you need\n100s of Split Leases, or source off market\nFinancially optimal. 45% less than Airbnb\nSafely store items while you're away.\nSame room, same bed. Unlike a hotel.\nStop playing room roulette!\nChoose Your Split Schedule\nExplore weekend listings\nExplore weeks of the month\nExplore weeknight listings\nChoose when to be a local\nFully-furnished spaces ensure move-in is a breeze.\nStore items like toiletries, a second monitor, work attire, and...\nForget HOAs. Switch neighborhoods seasonally, discover amazing flexibility.\nExplore Rentals\nCheck Out Some Listings\nOne Platt | Studio\nStudio - 1 bed - 1 bathroom - Free...\nPied-à-terre...\n2 bedrooms - 2 bed(s) - 1 bathroom - Free...\nFully furnished...\n1 bedroom - 1 bed - 1 bathroom - Free...\nFurnished Studio...\nStudio - 1 bed - 1 bathroom - Free...\nShow me more Rentals\nGet personal support\nCall\nFAQ\nChat\nEmail\nFor Hosts\nList Property Now\nHow to List\nLegal Section\nGuarantees\nFree House Manual\nFor Guests\nExplore Split Leases\nSuccess Stories\nSpeak to an Agent\nView FAQ\nCompany\nAbout Periodic Tenancy\nAbout the Team\nCareers at Split Lease\nView Blog\nEmergency assistance\nRefer a friend\nYou get $50 and they get $50 *after their first booking\nText Email\nShare now\nImport your listing from another site\nSubmit\nNow you can change your nights on the go.\nDownload at the App Store\nVoice-controlled concierge, at your service.\n\"Alexa, enable Split Lease\"\nTerms of Use\n© 2025 SplitLease\nFree Market Research\nSplit Lease\nHost with Us\nStay with Us\nSign In | Sign Up",
  "meta_tags": [
    {
      "name": "description",
      "content": "Commuting or Traveling? Rent a home by nights-of-the-week or weeks of the month. Live in multiple cities or skip your commute. Pay for the space, not cleaning fees and taxes. Have a space to share? Make predictable income by hosting repeat guests."
    },
    {
      "name": "og:title",
      "content": "Split Lease - the leader in periodic tenancy"
    },
    {
      "name": "og:site_name",
      "content": "Split Lease: nights-of-the-week rentals"
    },
    {
      "name": "og:description",
      "content": "Commuting or Traveling? Rent a home by nights-of-the-week or weeks of the month. Live in multiple cities or skip your commute. Pay for the space, not cleaning fees and taxes. Have a space to share? Make predictable income by hosting repeat guests."
    },
    {
      "name": "og:image",
      "content": "https://50bf0464e4735aabad1cc8848a0e8b8a.cdn.bubble.io/cdn-cgi/image/w=,h=,f=auto,dpr=1,fit=contain/f1627339735136x926685179094617600/ezgif.com-gif-maker%20%283%29.gif"
    },
    {
      "name": "og:url",
      "content": "https://www.split.lease/"
    },
    {
      "name": "og:type",
      "content": "website"
    },
    {
      "name": "twitter:card",
      "content": "summary_large_image"
    },
    {
      "name": "facebook-domain-verification",
      "content": "uun0ggpqa7zlb9l1nxwdh07awg8cnt"
    }
  ],
  "buttons": [
    "Explore Rentals",
    "Explore weekend listings",
    "Explore weeks of the month",
    "Explore weeknight listings",
    "Show me more Rentals",
    "Emergency assistance",
    "Share now",
    "Submit"
  ],
  "main_sections": [
    "Ongoing Rentals for Repeat Stays",
    "Only pay for nights you need",
    "Stop playing room roulette!",
    "Choose Your Split Schedule",
    "Choose when to be a local",
    "Check Out Some Listings",
    "Get personal support"
  ],
  "footer_sections": {
    "for_hosts": [
      "List Property Now",
      "How to List",
      "Legal Section",
      "Guarantees",
      "Free House Manual"
    ],
    "for_guests": [
      "Explore Split Leases",
      "Success Stories",
      "Speak to an Agent",
      "View FAQ"
    ],
    "company": [
      "About Periodic Tenancy",
      "About the Team",
      "Careers at Split Lease",
      "View Blog",
      "Emergency assistance"
    ]
  },
  "key_features": [
    "Select which days you'd like to stay in NYC and only pay for the nights you need",
    "100s of Split Leases, or source off market",
    "Financially optimal. 45% less than Airbnb",
    "Safely store items while you're away",
    "Same room, same bed. Unlike a hotel",
    "Fully-furnished spaces ensure move-in is a breeze",
    "Store items like toiletries, a second monitor, work attire",
    "Switch neighborhoods seasonally, discover amazing flexibility"
  ],
  "call_to_actions": [
    "Explore Rentals",
    "Explore weekend listings",
    "Explore weeks of the month",
    "Explore weeknight listings",
    "Show me more Rentals",
    "List Property Now",
    "Sign In | Sign Up"
  ],
  "support_options": [
    "Call",
    "FAQ",
    "Chat",
    "Email",
    "Speak to an Agent",
    "Emergency assistance"
  ],
  "app_availability": [
    "Download at the App Store",
    "\"Alexa, enable Split Lease\""
  ],
  "referral_program": "You get $50 and they get $50 *after their first booking",
  "copyright": "© 2025 SplitLease"
}